aynlp/__init__.py
aynlp/core.py
aynlp/lemmatizer.py
aynlp/ner.py
aynlp/pos_tagger.py
aynlp/sentiment.py
aynlp/stemmer.py
aynlp/stopwords.py
aynlp/tokenizer.py
build/lib/aynlp/__init__.py
build/lib/aynlp/core.py
build/lib/aynlp/lemmatizer.py
build/lib/aynlp/ner.py
build/lib/aynlp/pos_tagger.py
build/lib/aynlp/sentiment.py
build/lib/aynlp/stemmer.py
build/lib/aynlp/stopwords.py
build/lib/aynlp/tokenizer.py
aynlp-0.1.4.dist-info/METADATA
aynlp-0.1.4.dist-info/WHEEL
aynlp-0.1.4.dist-info/top_level.txt
aynlp-0.1.4.dist-info/RECORD
