Metadata-Version: 2.4
Name: aynlp
Version: 0.1.4
Summary: AYNLP: A lightweight NLP toolkit built by Ankit and Yash for tokenization, stemming, lemmatization, and more. Visit https://github.com/aijadugar/AYNLP to explore the project.
Home-page: https://github.com/aijadugar/AYNLP
Author: Ankit Bari <ankitbari@zohomail.in>, Yash Kerkar <kerkaryash5@gmail.com>
Author-email: Ankit Bari <ankitbari@zohomail.in>, Yash Kerkar <kerkaryash5@gmail.com>
License: MIT
Keywords: python,aynlp,nlp,natural-language-processing,tokenization,lemmatization,stemming,pos-tagging,ner,sentiment-analysis,text-processing,Ankit Bari,Yash Kerkar
Classifier: Development Status :: 3 - Alpha
Classifier: Intended Audience :: Developers
Classifier: Topic :: Scientific/Engineering :: Artificial Intelligence
Classifier: Programming Language :: Python :: 3
Classifier: License :: OSI Approved :: MIT License
Classifier: Operating System :: Unix
Classifier: Operating System :: MacOS :: MacOS X
Classifier: Operating System :: Microsoft :: Windows
Requires-Python: >=3.7
Requires-Dist: numpy<2.0,>=1.26.0
Requires-Dist: scipy<1.28.0,>=1.11.0
Requires-Dist: spacy>=3.7.0
Requires-Dist: nltk>=3.8.1
Requires-Dist: tabulate>=0.9.0
Requires-Dist: textblob>=0.17.1
Dynamic: author
Dynamic: home-page
Dynamic: requires-python
